MANIFEST.in
README.rst
bootstrap-buildout.py
buildout.cfg
develop.cfg
requirements.txt
setup.py
version.txt
bob/__init__.py
bob.example.faceverify.egg-info/PKG-INFO
bob.example.faceverify.egg-info/SOURCES.txt
bob.example.faceverify.egg-info/dependency_links.txt
bob.example.faceverify.egg-info/entry_points.txt
bob.example.faceverify.egg-info/requires.txt
bob.example.faceverify.egg-info/top_level.txt
bob.example.faceverify.egg-info/zip-safe
bob/example/__init__.py
bob/example/faceverify/__init__.py
bob/example/faceverify/dct_ubm.py
bob/example/faceverify/eigenface.py
bob/example/faceverify/gabor_graph.py
bob/example/faceverify/tests.py
bob/example/faceverify/utils.py
bob/example/faceverify/data/dct_feature.hdf5
bob/example/faceverify/data/dct_model.hdf5
bob/example/faceverify/data/dct_probe.hdf5
bob/example/faceverify/data/dct_ubm.hdf5
bob/example/faceverify/data/gabor_model.hdf5
bob/example/faceverify/data/gabor_probe.hdf5
bob/example/faceverify/data/pca_model.hdf5
bob/example/faceverify/data/pca_probe.hdf5
bob/example/faceverify/data/pca_projector.hdf5
doc/conf.py
doc/dct_ubm.png
doc/eigenface.png
doc/examples.rst
doc/gabor_graph.png
doc/index.rst
doc/installation.rst
doc/img/logo.png