Metadata-Version: 1.1
Name: bob.example.faceverify
Version: 2.1.2
Summary: Example for using Bob to create three distinct face verification systems
Home-page: http://pypi.python.org/pypi/bob.example.faceverify
Author: Manuel Guenther
Author-email: manuel.guenther@idiap.ch
License: GPLv3
Platform: UNKNOWN
Classifier: Framework :: Bob
Classifier: Development Status :: 4 - Beta
Classifier: License :: OSI Approved :: GNU General Public License v3 (GPLv3)
Classifier: Intended Audience :: Education
Classifier: Intended Audience :: Science/Research
Classifier: Natural Language :: English
Classifier: Programming Language :: Python
Classifier: Programming Language :: Python :: 3
